streamlake/__init__.py
streamlake-0.1.0.dist-info/METADATA
streamlake-0.1.0.dist-info/WHEEL
streamlake-0.1.0.dist-info/RECORD
